thoth/__init__.py
thoth/__main__.py
thoth/cli.py
thoth/handler/__init__.py
thoth/handler/base_handler.py
thoth/handler/dt.py
thoth/static/favicon.ico
thoth/static/text/dt/eda.md
thoth/static/text/dt/intro.md
thoth/static/text/dt/playground.md
thoth/thoth_runner.py
thoth/utils.py
thoth_ml-0.1.0.dist-info/entry_points.txt
thoth_ml-0.1.0.dist-info/WHEEL
thoth_ml-0.1.0.dist-info/METADATA
thoth_ml-0.1.0.dist-info/RECORD
