Metadata-Version: 2.1
Name: thoth-ml
Version: 0.1.0
Summary: Interactive playground for machine learning
Home-page: https://thoth-ml.readthedocs.io/en/latest/
Author: Felix Lonergan Corti
Author-email: felix.lonergan@gmail.com
Requires-Python: >=3.7,<3.11
Classifier: Programming Language :: Python :: 3
Classifier: Programming Language :: Python :: 3.10
Classifier: Programming Language :: Python :: 3.7
Classifier: Programming Language :: Python :: 3.8
Classifier: Programming Language :: Python :: 3.9
Provides-Extra: docs
Requires-Dist: click (>=8.0,<9.0)
Requires-Dist: graphviz (>=0.18,<1.0)
Requires-Dist: isort (>=5.10,<6.0)
Requires-Dist: jsonschema (==3.2)
Requires-Dist: mkdocs (>=1.3.0,<1.4.0); extra == "docs"
Requires-Dist: mkdocs-click (>=0.5.0,<0.6.0); extra == "docs"
Requires-Dist: mkdocs-include-markdown-plugin (>=3.3.0,<3.4.0); extra == "docs"
Requires-Dist: mkdocs-material (>=8.2.9,<8.3.0); extra == "docs"
Requires-Dist: mkdocstrings[python] (>=0.18.1,<0.19.0); extra == "docs"
Requires-Dist: pandas (>=1.3.4,<1.4.0)
Requires-Dist: scikit-learn (>=1.0.1,<1.1.0)
Requires-Dist: streamlit (>=1.8,<2.0)
Requires-Dist: watchdog (>=2.1.6,<2.2.0)
Project-URL: Documentation, https://thoth-ml.readthedocs.io/en/latest/
Project-URL: Repository, https://github.com/FelixLonergan/thoth
